pretty_flag/__init__.py
pretty_flag-0.1.1.dist-info/METADATA
pretty_flag-0.1.1.dist-info/WHEEL
pretty_flag-0.1.1.dist-info/top_level.txt
pretty_flag-0.1.1.dist-info/RECORD
