Metadata-Version: 2.4
Name: pretty-flag
Version: 0.1.1
Summary: A pretty way to print flags in CTFs
Requires-Python: >=3.12
Requires-Dist: rich>=14.0.0
